pyperclipfix/__init__.py
pyperclipfix/__main__.py
pyperclipfix-1.9.4.dist-info/AUTHORS.txt
pyperclipfix-1.9.4.dist-info/LICENSE.txt
pyperclipfix-1.9.4.dist-info/METADATA
pyperclipfix-1.9.4.dist-info/WHEEL
pyperclipfix-1.9.4.dist-info/top_level.txt
pyperclipfix-1.9.4.dist-info/RECORD
